{
  "onboarding2-a": {
    "match": {
        "version": "^4[6-9]\\..*"
    },
    "buckets": {
      "min": "0",
      "max": "33"
    }
  },
  "onboarding2-b": {
    "match": {
        "version": "^4[6-9]\\..*"
    },
    "buckets": {
      "min": "33",
      "max": "66"
    }
  },
  "onboarding2-c": {
    "match": {
        "version": "^4[6-9]\\..*"
    },
    "buckets": {
      "min": "66",
      "max": "100"
    }
  },
  "bookmark-history-menu": {
    "match": {
      "appId": "org.mozilla.fennec"
    },
    "buckets": {
      "min": "0",
      "max": "100"
    }
  }
}
